LICENSE
README.md
setup.py
bin/giig
giig/__init__.py
giig/giig.py
giig.egg-info/PKG-INFO
giig.egg-info/SOURCES.txt
giig.egg-info/dependency_links.txt
giig.egg-info/requires.txt
giig.egg-info/top_level.txt