Metadata-Version: 2.1
Name: giig
Version: 0.3.2
Summary: CLI for gitignore.io
Home-page: https://github.com/lagerfeuer/gitignore
Author: Lukas Deutz
Author-email: github@deutz.io
License: MIT
Keywords: gitignore git cli
Classifier: Programming Language :: Python :: 3
Requires-Python: >=3
License-File: LICENSE
